access_token_manager/__init__.py
access_token_manager/access_token_manager.py
thinkbig_products_walmart_access_token_manager-0.2.7.dist-info/METADATA
thinkbig_products_walmart_access_token_manager-0.2.7.dist-info/WHEEL
thinkbig_products_walmart_access_token_manager-0.2.7.dist-info/top_level.txt
thinkbig_products_walmart_access_token_manager-0.2.7.dist-info/RECORD
