Metadata-Version: 2.2
Name: thinkbig_products_walmart_access_token_manager
Version: 0.2.7
Summary: A package for managing Walmart Marketplace API access tokens
Home-page: https://github.com/ThinkBig-Products/walmart_access_token_manager
Author: ThinkBig Products
Author-email: your.email@example.com
Project-URL: GitHub, https://github.com/ThinkBig-Products/walmart_access_token_manager
Project-URL: Bug Tracker, https://github.com/ThinkBig-Products/walmart_access_token_manager/issues
Classifier: Programming Language :: Python :: 3
Classifier: License :: OSI Approved :: MIT License
Classifier: Operating System :: OS Independent
Requires-Python: >=3.6
Requires-Dist: boto3
Requires-Dist: requests
Requires-Dist: pycryptodome
Requires-Dist: mysql-connector-python
Dynamic: author
Dynamic: author-email
Dynamic: classifier
Dynamic: description
Dynamic: description-content-type
Dynamic: home-page
Dynamic: project-url
Dynamic: requires-dist
Dynamic: requires-python
Dynamic: summary
